{
  "project_info": {
    "project_number": "840557391069",
    "project_id": "chat-app-a4268",
    "storage_bucket": "chat-app-a4268.appspot.com"
  },
  "client": [
    {
      "client_info": {
        "mobilesdk_app_id": "1:840557391069:android:9b9df64045730e8ff17f34",
        "android_client_info": {
          "package_name": "com.example.chatapp"
        }
      },
      "oauth_client": [
        {
          "client_id": "840557391069-v1796rlqc6jb2mgq7ojvjjlc6k9tqlk9.apps.googleusercontent.com",
          "client_type": 3
        }
      ],
      "api_key": [
        {
          "current_key": "AIzaSyDg-vbrXfs28Pv3RYXMzDgXEadiOzDwKX8"
        }
      ],
      "services": {
        "appinvite_service": {
          "other_platform_oauth_client": [
            {
              "client_id": "840557391069-v1796rlqc6jb2mgq7ojvjjlc6k9tqlk9.apps.googleusercontent.com",
              "client_type": 3
            }
          ]
        }
      }
    }
  ],
  "configuration_version": "1"
}